js_regex/__init__.py
js_regex/_impl.py
js_regex/py.typed
js_regex-1.0.1.dist-info/LICENSE
js_regex-1.0.1.dist-info/METADATA
js_regex-1.0.1.dist-info/WHEEL
js_regex-1.0.1.dist-info/top_level.txt
js_regex-1.0.1.dist-info/RECORD
