Metadata-Version: 2.1
Name: js-regex
Version: 1.0.1
Summary: A thin compatibility layer to use Javascript regular expressions in Python
Home-page: https://github.com/Zac-HD/js-regex
Author: Zac Hatfield-Dodds
Author-email: zac@hypothesis.works
License: MPL 2.0
Keywords: python javascript regex compatibility
Platform: UNKNOWN
Classifier: Development Status :: 4 - Beta
Classifier: Intended Audience :: Developers
Classifier: License :: OSI Approved :: Mozilla Public License 2.0 (MPL 2.0)
Classifier: Programming Language :: JavaScript
Classifier: Programming Language :: Python
Classifier: Programming Language :: Python :: 3
Classifier: Programming Language :: Python :: 3.6
Classifier: Programming Language :: Python :: 3.7
Classifier: Topic :: Software Development :: Testing
Classifier: Topic :: Text Processing
Classifier: Typing :: Typed
Requires-Python: >=2.7, !=3.0.*, !=3.1.*, !=3.2.*, !=3.3.*, !=3.4.*
